{
  "project_info": {
    "project_number": "845326677183",
    "project_id": "timeline-de197",
    "storage_bucket": "timeline-de197.appspot.com"
  },
  "client": [
    {
      "client_info": {
        "mobilesdk_app_id": "1:845326677183:android:017de220bfaa944723420a",
        "android_client_info": {
          "package_name": "com.example.timeLine"
        }
      },
      "oauth_client": [
        {
          "client_id": "845326677183-8h80okmesebni6poee8qu5h4fp2om1v2.apps.googleusercontent.com",
          "client_type": 1,
          "android_info": {
            "package_name": "com.example.timeLine",
            "certificate_hash": "2530df778c3e6a5160d486e59e9b8f9c12e13593"
          }
        },
        {
          "client_id": "845326677183-231l3lmnuqmu5p45oole6d28stou3use.apps.googleusercontent.com",
          "client_type": 3
        }
      ],
      "api_key": [
        {
          "current_key": "AIzaSyAH-Gx0si_DAj02rYIkO_unCMSfKiFKP6M"
        }
      ],
      "services": {
        "appinvite_service": {
          "other_platform_oauth_client": [
            {
              "client_id": "845326677183-231l3lmnuqmu5p45oole6d28stou3use.apps.googleusercontent.com",
              "client_type": 3
            }
          ]
        }
      }
    }
  ],
  "configuration_version": "1"
}